{"trial_id": "2418", "hyperparameters": {"space": [{"class_name": "Choice", "config": {"name": "activation", "default": "relu", "conditions": [], "values": ["relu", "sigmoid", "tanh", "linear"], "ordered": false}}, {"class_name": "Int", "config": {"name": "first_units", "default": null, "conditions": [], "min_value": 1, "max_value": 100, "step": 5, "sampling": null}}, {"class_name": "Int", "config": {"name": "num_layers", "default": null, "conditions": [], "min_value": 1, "max_value": 12, "step": 1, "sampling": null}}, {"class_name": "Int", "config": {"name": "units_0", "default": null, "conditions": [], "min_value": 1, "max_value": 100, "step": 5, "sampling": null}}, {"class_name": "Int", "config": {"name": "units_1", "default": null, "conditions": [], "min_value": 1, "max_value": 100, "step": 5, "sampling": null}}, {"class_name": "Int", "config": {"name": "units_2", "default": null, "conditions": [], "min_value": 1, "max_value": 100, "step": 5, "sampling": null}}, {"class_name": "Int", "config": {"name": "units_3", "default": null, "conditions": [], "min_value": 1, "max_value": 100, "step": 5, "sampling": null}}, {"class_name": "Int", "config": {"name": "units_4", "default": null, "conditions": [], "min_value": 1, "max_value": 100, "step": 5, "sampling": null}}, {"class_name": "Int", "config": {"name": "units_5", "default": null, "conditions": [], "min_value": 1, "max_value": 100, "step": 5, "sampling": null}}, {"class_name": "Int", "config": {"name": "units_6", "default": null, "conditions": [], "min_value": 1, "max_value": 100, "step": 5, "sampling": null}}, {"class_name": "Int", "config": {"name": "units_7", "default": null, "conditions": [], "min_value": 1, "max_value": 100, "step": 5, "sampling": null}}, {"class_name": "Int", "config": {"name": "units_8", "default": null, "conditions": [], "min_value": 1, "max_value": 100, "step": 5, "sampling": null}}, {"class_name": "Int", "config": {"name": "units_9", "default": null, "conditions": [], "min_value": 1, "max_value": 100, "step": 5, "sampling": null}}, {"class_name": "Int", "config": {"name": "units_10", "default": null, "conditions": [], "min_value": 1, "max_value": 100, "step": 5, "sampling": null}}, {"class_name": "Int", "config": {"name": "units_11", "default": null, "conditions": [], "min_value": 1, "max_value": 100, "step": 5, "sampling": null}}], "values": {"activation": "sigmoid", "first_units": 56, "num_layers": 3, "units_0": 46, "units_1": 6, "units_2": 16, "units_3": 76, "units_4": 56, "units_5": 26, "units_6": 81, "units_7": 71, "units_8": 76, "units_9": 71, "units_10": 16, "units_11": 21, "tuner/epochs": 12, "tuner/initial_epoch": 4, "tuner/bracket": 4, "tuner/round": 2, "tuner/trial_id": "2384"}}, "metrics": {"metrics": {"loss": {"direction": "min", "observations": [{"value": [0.5716716647148132], "step": 5}]}, "accuracy": {"direction": "max", "observations": [{"value": [0.7309905290603638], "step": 5}]}, "val_loss": {"direction": "min", "observations": [{"value": [0.5707479119300842], "step": 5}]}, "val_accuracy": {"direction": "max", "observations": [{"value": [0.7331778407096863], "step": 5}]}}}, "score": 0.7331778407096863, "best_step": 5, "status": "COMPLETED"}